TorchDiffEqPack/__init__.py
TorchDiffEqPack/misc.py
TorchDiffEqPack/utils.py
TorchDiffEqPack/odesolver/__init__.py
TorchDiffEqPack/odesolver/adaptive_grid_solver.py
TorchDiffEqPack/odesolver/autograd_functional.py
TorchDiffEqPack/odesolver/base.py
TorchDiffEqPack/odesolver/fixed_grid_solver.py
TorchDiffEqPack/odesolver/ode_solver.py
TorchDiffEqPack/odesolver/stiff_ode_solver.py
TorchDiffEqPack/odesolver/symplectic.py
TorchDiffEqPack/odesolver/tuple_to_tensor_wrapper.py
TorchDiffEqPack/odesolver_mem/__init__.py
TorchDiffEqPack/odesolver_mem/adjoint.py
TorchDiffEqPack/odesolver_mem/adjoint_mem.py
TorchDiffEqPack/odesolver_mem/odesolver_endtime.py
TorchDiffEqPack-1.0.1.dist-info/METADATA
TorchDiffEqPack-1.0.1.dist-info/WHEEL
TorchDiffEqPack-1.0.1.dist-info/top_level.txt
TorchDiffEqPack-1.0.1.dist-info/RECORD
