Metadata-Version: 2.1
Name: TorchDiffEqPack
Version: 1.0.1
Summary: PyTorch implementation of reverse-accurate ODE solvers for Neural ODEs
Home-page: https://juntang-zhuang.github.io/torch_diff_eq_pack/
Author: Juntang Zhuang
Author-email: j.zhuang@yale.edu
License: UNKNOWN
Platform: UNKNOWN
Classifier: Programming Language :: Python :: 3
Classifier: License :: OSI Approved :: MIT License
Classifier: Operating System :: OS Independent
Requires-Python: >=3.6
Requires-Dist: torch
